Metadata-Version: 2.1
Name: SQLAlchemy
Version: 2.0.44
Summary: Database Abstraction Library
Home-page: https://www.sqlalchemy.org
Author: Mike Bayer
Author-email: mike_mp@zzzcomputing.com
License: MIT
Project-URL: Documentation, https://docs.sqlalchemy.org
Project-URL: Issue Tracker, https://github.com/sqlalchemy/sqlalchemy/
Classifier: Development Status :: 5 - Production/Stable
Classifier: Intended Audience :: Developers
Classifier: Operating System :: OS Independent
Classifier: Programming Language :: Python
Classifier: Programming Language :: Python :: 3
Classifier: Programming Language :: Python :: 3.7
Classifier: Programming Language :: Python :: 3.8
Classifier: Programming Language :: Python :: 3.9
Classifier: Programming Language :: Python :: 3.10
Classifier: Programming Language :: Python :: 3.11
Classifier: Programming Language :: Python :: 3.12
Classifier: Programming Language :: Python :: 3.13
Classifier: Programming Language :: Python :: Implementation :: CPython
Classifier: Programming Language :: Python :: Implementation :: PyPy
Classifier: Topic :: Database :: Front-Ends
Requires-Python: >=3.7
License-File: LICENSE
Requires-Dist: typing-extensions >=4.6.0
Requires-Dist: greenlet >=1 ; platform_machine == "aarch64" or (platform_machine == "ppc64le" or (platform_machine == "x86_64" or (platform_machine == "amd64" or (platform_machine == "AMD64" or (platform_machine == "win32" or platform_machine == "WIN32")))))
Requires-Dist: importlib-metadata ; python_version < "3.8"
Provides-Extra: aiomysql
Requires-Dist: greenlet >=1 ; extra == 'aiomysql'
Requires-Dist: aiomysql >=0.2.0 ; extra == 'aiomysql'
Provides-Extra: aioodbc
Requires-Dist: greenlet >=1 ; extra == 'aioodbc'
Requires-Dist: aioodbc ; extra == 'aioodbc'
Provides-Extra: aiosqlite
Requires-Dist: greenlet >=1 ; extra == 'aiosqlite'
Requires-Dist: aiosqlite ; extra == 'aiosqlite'
Requires-Dist: typing-extensions !=3.10.0.1 ; extra == 'aiosqlite'
Provides-Extra: asyncio
Requires-Dist: greenlet >=1 ; extra == 'asyncio'
Provides-Extra: asyncmy
Requires-Dist: greenlet >=1 ; extra == 'asyncmy'
Requires-Dist: asyncmy !=0.2.4,!=0.2.6,>=0.2.3 ; extra == 'asyncmy'
Provides-Extra: mariadb_connector
Requires-Dist: mariadb !=1.1.10,!=1.1.2,!=1.1.5,>=1.0.1 ; extra == 'mariadb_connector'
Provides-Extra: mssql
Requires-Dist: pyodbc ; extra == 'mssql'
Provides-Extra: mssql_pymssql
Requires-Dist: pymssql ; extra == 'mssql_pymssql'
Provides-Extra: mssql_pyodbc
Requires-Dist: pyodbc ; extra == 'mssql_pyodbc'
Provides-Extra: mypy
Requires-Dist: mypy >=0.910 ; extra == 'mypy'
Provides-Extra: mysql
Requires-Dist: mysqlclient >=1.4.0 ; extra == 'mysql'
Provides-Extra: mysql_connector
Requires-Dist: mysql-connector-python ; extra == 'mysql_connector'
Provides-Extra: oracle
Requires-Dist: cx-oracle >=8 ; extra == 'oracle'
Provides-Extra: oracle_oracledb
Requires-Dist: oracledb >=1.0.1 ; extra == 'oracle_oracledb'
Provides-Extra: postgresql
Requires-Dist: psycopg2 >=2.7 ; extra == 'postgresql'
Provides-Extra: postgresql_asyncpg
Requires-Dist: greenlet >=1 ; extra == 'postgresql_asyncpg'
Requires-Dist: asyncpg ; extra == 'postgresql_asyncpg'
Provides-Extra: postgresql_pg8000
Requires-Dist: pg8000 >=1.29.1 ; extra == 'postgresql_pg8000'
Provides-Extra: postgresql_psycopg
Requires-Dist: psycopg >=3.0.7 ; extra == 'postgresql_psycopg'
Provides-Extra: postgresql_psycopg2binary
Requires-Dist: psycopg2-binary ; extra == 'postgresql_psycopg2binary'
Provides-Extra: postgresql_psycopg2cffi
Requires-Dist: psycopg2cffi ; extra == 'postgresql_psycopg2cffi'
Provides-Extra: postgresql_psycopgbinary
Requires-Dist: psycopg[binary] >=3.0.7 ; extra == 'postgresql_psycopgbinary'
Provides-Extra: pymysql
Requires-Dist: pymysql ; extra == 'pymysql'
Provides-Extra: sqlcipher
Requires-Dist: sqlcipher3-binary ; extra == 'sqlcipher'
